rwse_checker/__init__.py
rwse_checker/data/en_sets_ci.txt
rwse_checker/example.py
rwse_checker/rwse.py
rwse_checker-0.0.4.dist-info/LICENSE
rwse_checker-0.0.4.dist-info/METADATA
rwse_checker-0.0.4.dist-info/WHEEL
rwse_checker-0.0.4.dist-info/RECORD
