Metadata-Version: 2.3
Name: rwse-checker
Version: 0.0.4
Summary: Finding and correcting real-word spelling errors using masked language models.
License: MIT
Author: dmnc-grdnr
Author-email: dmnc.crl.grdnr@gmail.com
Requires-Python: >=3.9,<4.0
Classifier: License :: OSI Approved :: MIT License
Classifier: Programming Language :: Python :: 3
Classifier: Programming Language :: Python :: 3.9
Classifier: Programming Language :: Python :: 3.10
Classifier: Programming Language :: Python :: 3.11
Classifier: Programming Language :: Python :: 3.12
Classifier: Programming Language :: Python :: 3.13
Requires-Dist: dkpro-cassis (>=0.9.1)
Requires-Dist: pytest (>=7.4.3,<8.0.0)
Requires-Dist: torch (>=2.4.1,<3.0.0)
Requires-Dist: transformers (>=4.48.1,<5.0.0)
